helloworldlib/__init__.py
helloworldlib/helloworld.py
hellowrldpakg888-0.0.1.dist-info/METADATA
hellowrldpakg888-0.0.1.dist-info/WHEEL
hellowrldpakg888-0.0.1.dist-info/top_level.txt
hellowrldpakg888-0.0.1.dist-info/RECORD
