Metadata-Version: 2.1
Name: hellowrldpakg888
Version: 0.0.1
Summary: Basic Hello World Package
Home-page: UNKNOWN
Author: SMS
Author-email: UNKNOWN
License: UNKNOWN
Keywords: python,helloworld
Platform: UNKNOWN
Classifier: Development Status :: 1 - Planning
Classifier: Intended Audience :: Developers
Classifier: Programming Language :: Python :: 3
Classifier: Operating System :: Unix
Classifier: Operating System :: MacOS :: MacOS X
Classifier: Operating System :: Microsoft :: Windows
